{
  "indexes": [
    {
      "collectionGroup": "payouts",
      "queryScope": "COLLECTION",
      "fields": [
        { "fieldPath": "userId", "order": "ASCENDING" },
        { "fieldPath": "createdAt", "order": "DESCENDING" }
      ]
    },
    {
      "collectionGroup": "payouts",
      "queryScope": "COLLECTION",
      "fields": [
        { "fieldPath": "userId", "order": "ASCENDING" },
        { "fieldPath": "rentalId", "order": "ASCENDING" }
      ]
    },
    {
      "collectionGroup": "rentals",
      "queryScope": "COLLECTION",
      "fields": [
        { "fieldPath": "status", "order": "ASCENDING" },
        { "fieldPath": "payoutFrozen", "order": "ASCENDING" },
        { "fieldPath": "payoutEligibleAt", "order": "ASCENDING" }
      ]
    }
  ],
  "fieldOverrides": []
}